pybricks_jedi/__init__.py
pybricks_jedi-1.17.0.dist-info/LICENSE
pybricks_jedi-1.17.0.dist-info/METADATA
pybricks_jedi-1.17.0.dist-info/WHEEL
pybricks_jedi-1.17.0.dist-info/RECORD
