Metadata-Version: 2.3
Name: pybricks_jedi
Version: 1.17.0
Summary: Code completion for Pybricks.
License: MIT
Author: The Pybricks Authors
Author-email: team@pybricks.com
Requires-Python: >=3.10,<3.12
Classifier: License :: OSI Approved :: MIT License
Classifier: Programming Language :: Python :: 3
Classifier: Programming Language :: Python :: 3.10
Classifier: Programming Language :: Python :: 3.11
Requires-Dist: docstring-parser (==0.14.1)
Requires-Dist: jedi (==0.18.1)
Requires-Dist: pybricks (==3.6.0b5)
Requires-Dist: typing-extensions (==4.2.0)
